flask_raspi_gpio_control/__init__.py
flask_raspi_gpio_control-0.0.1.dist-info/METADATA
flask_raspi_gpio_control-0.0.1.dist-info/WHEEL
flask_raspi_gpio_control-0.0.1.dist-info/top_level.txt
flask_raspi_gpio_control-0.0.1.dist-info/RECORD
